gitlab_caller/__init__.py
gitlab_caller/client.py
gitlab_caller/http.py
gitlab_caller/session.py
gitlab_caller/utils.py
gitlab_caller-0.1.0.dist-info/METADATA
gitlab_caller-0.1.0.dist-info/WHEEL
gitlab_caller-0.1.0.dist-info/top_level.txt
gitlab_caller-0.1.0.dist-info/RECORD
