Metadata-Version: 2.1
Name: gitlab-caller
Version: 0.1.0
Summary: Python SDK for Gitlab API
Home-page: UNKNOWN
Author: wuwentao
License: UNKNOWN
Platform: UNKNOWN
Classifier: Operating System :: OS Independent
Classifier: License :: OSI Approved :: MIT License
Classifier: Programming Language :: Python :: 3.5
Classifier: Programming Language :: Python :: 3.6
Classifier: Programming Language :: Python :: 3.7
Requires-Python: >=3.5
Requires-Dist: requests
